README
setup.py
ex1/__init__.py
ex1/linearRegression.py
ex2/__init__.py
ex2/logisticClassification.py
ex3/__init__.py
ex3/multiClassification.py
machineLearningStanford.egg-info/PKG-INFO
machineLearningStanford.egg-info/SOURCES.txt
machineLearningStanford.egg-info/dependency_links.txt
machineLearningStanford.egg-info/not-zip-safe
machineLearningStanford.egg-info/requires.txt
machineLearningStanford.egg-info/top_level.txt