Metadata-Version: 1.0
Name: machineLearningStanford
Version: 0.0
Summary: Machine Learning Stanford
Home-page: https://github.com/ZianLai/machineLearningStanford
Author: Lai, Chih-An
Author-email: chihan.lai@gmail.com
License: UNKNOWN
Platform: UNKNOWN
